<?xml version="1.0" encoding="utf-8"?>
<Defs>
    <ThingDef ParentName="CosmereMoteAllomancyAura">
        <defName>Cosmere_Mote_Brass_Aura</defName>
        <label>brass aura</label>
        <graphicData>
            <shaderParameters>
                <_PulseTime>10</_PulseTime>
                <_Speed>1</_Speed>
                <_TrailLength>0.05</_TrailLength>
                <_Color>(0.686, 0.580, 0.357, 1)</_Color>
                <_Color2>(0.686, 0.580, 0.357, 0.2)</_Color2>
            </shaderParameters>
        </graphicData>
    </ThingDef>
</Defs>