<?xml version="1.0" encoding="utf-8"?>
<!--The above line is the start of every XML file. Just ignore it-->
<ModMetaData>
    <name>Cosmere - Core</name>
    <description>This mod adds the core magic system from Brandon Sanderson's Cosmere Universe into Rimworld (Investiture &amp; Connection)</description>
    <author>CryptikLemur</author>
    <supportedVersions>
        <li>1.5</li>
    </supportedVersions>
    <packageId>cryptiklemur.cosmere.core</packageId>
    <modDependencies>
        <li>
            <packageId>cryptiklemur.cosmere.framework</packageId>
            <displayName>Cosmere - Framework</displayName>
            <downloadUrl>https://github.com/RimworldCosmere/RimworldCosmere/releases/latest</downloadUrl>
        </li>
    </modDependencies>
    <forceLoadAfter>
        <li>cryptiklemur.cosmere.framework</li>
    </forceLoadAfter>
</ModMetaData>